{
  "schemaVersion": 1,
  "id": "valvesprint",
  "version": "${version}",
  "name": "ValveSprint",
  "description": "Sprinting like Valve games.",
  "authors": [
    "Spelis"
  ],
  "contact": {
    "email": "spelis.loves.rust@gmail.com",
    "issues": "https://github.com/spelis/ValveSprint/issues",
    "homepage": "https://spelis.projnull.eu",
    "sources": "https://github.com/spelis/ValveSprint"
  },
  "license": "MIT",
  "icon": "assets/valvesprint/icon.png",
  "environment": "client",
  "entrypoints": {
    "fabric-datagen": [
      "eu.projnull.spelis.valvesprint.client.ValveSprintDataGenerator"
    ],
    "client": [
      "eu.projnull.spelis.valvesprint.client.ValveSprintClient"
    ]
  },
  "mixins": [
    {
      "config": "valvesprint.client.mixins.json",
      "environment": "client"
    }
  ],
  "depends": {
    "fabricloader": ">=0.16.0",
    "fabric": "*",
    "minecraft": ">=1.16.0"
  }
}
